{"meta": {"source": "USGS", "generated_utc": "2026-05-17T19:05:22.703643+00:00", "days": 30, "minmag": 2.5, "count": 1966, "query_url": "https://earthquake.usgs.gov/fdsnws/event/1/query?format=geojson&starttime=2026-04-17T19:05:21&endtime=2026-05-17T19:05:21&minmagnitude=2.5&orderby=time"}, "events": [{"id": "us6000svgl", "time": 1778022152667, "mag": 4.1, "place": "34 km S of Marina di Camerota, Italy", "url": "https://earthquake.usgs.gov/earthquakes/eventpage/us6000svgl", "lat": 39.6922, "lon": 15.3441, "depth": 307.255}, {"id": "us7000sia3", "time": 1777941351496, "mag": 4, "place": "10 km SE of Draž, Croatia", "url": "https://earthquake.usgs.gov/earthquakes/eventpage/us7000sia3", "lat": 45.7705, "lon": 18.8799, "depth": 10}, {"id": "us6000ssx8", "time": 1777170243657, "mag": 4.2, "place": "1 km SSW of Walenstadt, Switzerland", "url": "https://earthquake.usgs.gov/earthquakes/eventpage/us6000ssx8", "lat": 47.1103, "lon": 9.3034, "depth": 5}, {"id": "us6000sstf", "time": 1777117382229, "mag": 4, "place": "41 km WSW of Cittadella del Capo, Italy", "url": "https://earthquake.usgs.gov/earthquakes/eventpage/us6000sstf", "lat": 39.4059, "lon": 15.4387, "depth": 272.386}]}